qcom_nandc_pagify/__init__.py
qcom_nandc_pagify/__main__.py
qcom_nandc_pagify/_main.py
qcom_nandc_pagify/chunk.py
qcom_nandc_pagify/ecc.py
qcom_nandc_pagify/page.py
qcom_nandc_pagify-0.2.dist-info/METADATA
qcom_nandc_pagify-0.2.dist-info/WHEEL
qcom_nandc_pagify-0.2.dist-info/entry_points.txt
qcom_nandc_pagify-0.2.dist-info/top_level.txt
qcom_nandc_pagify-0.2.dist-info/RECORD
