Metadata-Version: 2.1
Name: qcom-nandc-pagify
Version: 0.2
Summary: Raw Image to Qualcomm NAND controller image converter
Home-page: https://github.com/ecsv/qcom-nandc-pagify
Author: Sven Eckelmann
Author-email: sven@narfation.org
License: MIT
Project-URL: Bug Tracker, https://github.com/ecsv/qcom-nandc-pagify/issues
Classifier: Programming Language :: Python :: 3
Classifier: License :: OSI Approved :: MIT License
Classifier: Operating System :: OS Independent
Requires-Python: >=3.5
Requires-Dist: bchlib >=1
Requires-Dist: reedsolo >=1
